<?xml version="1.0"?>

<member id="m_tushar" group="g_istlab g_sense" joined="20151214">
    <givenname>Tushar</givenname>
	<surname>Sharma</surname>
	<memb_title>Mr.</memb_title>
	<email>tushar@aueb.gr</email>
	<web_site>http://sharmatushar.blogspot.in/</web_site>
	<office_address>Athens University of Economics and Business Main Building, Derigny ct, 3rd floor, Athens, Greece.</office_address>
    <postal_address>
		76 Patission str,
		104 34,
		Athens, Greece
	</postal_address>
	<photo>../images/m_tushar.jpg</photo>

	<shortcv>
	    <p> <i>Tushar Sharma</i> is a researcher and PhD candidate at the Athens University of Economics and Business (AUEB), Department of Management Science and Technology. He is a member of the EuroSys society and the <a href="../groups/g_sense-details.html">SENSE</a> group.</p>
        <p>Earlier, he worked with Siemens Research and Technology Center, Bangalore, India for more than 7 years. The topics related to software design, refactoring, design smells, code and design quality, technical debt, design patterns, and change impact analysis define his career interests. He has an MS (by research) degree in Computer Science from the Indian Institute of Technology-Madras (IIT-M), Chennai, India, where he specialised in design patterns and refactoring. He co-authored the book "Refactoring for Software Design Smells: Managing Technical Debt" published by Morgan Kaufmann in November 2014. Additionally, he has also co-authored books for Oracle certifications for Java. He is an IEEE Senior Member.</p>
	</shortcv>

	<phd-info completed="0"
			  supervisor="m_dds"
			  startdate="20151214">
		<phd-title>Software Engineering in Enterprise Cloud Applications</phd-title>
		<phd-summary></phd-summary>
		</phd-info>	
</member>
